ballet_assemble/__init__.py
ballet_assemble/app.py
ballet_assemble/handlers.py
ballet_assemble-0.8.8.data/data/etc/jupyter/jupyter_notebook_config.d/ballet-assemble.json
ballet_assemble-0.8.8.data/data/share/jupyter/lab/extensions/ballet-assemble-0.8.8.tgz
ballet_assemble-0.8.8.dist-info/LICENSE
ballet_assemble-0.8.8.dist-info/METADATA
ballet_assemble-0.8.8.dist-info/WHEEL
ballet_assemble-0.8.8.dist-info/top_level.txt
ballet_assemble-0.8.8.dist-info/RECORD
