Metadata-Version: 2.1
Name: ballet-assemble
Version: 0.8.8
Summary: Submit ballet modules from within JupyterLab
Home-page: https://github.com/ballet/ballet-assemble
Author: Micah Smith
License: MIT
Keywords: Jupyter,JupyterLab
Platform: Linux
Platform: Mac OS X
Platform: Windows
Classifier: License :: OSI Approved :: BSD License
Classifier: Programming Language :: Python
Classifier: Programming Language :: Python :: 3
Classifier: Programming Language :: Python :: 3.6
Classifier: Programming Language :: Python :: 3.7
Classifier: Programming Language :: Python :: 3.8
Classifier: Framework :: Jupyter
Requires-Dist: ballet
Requires-Dist: black (==19.10b0)
Requires-Dist: funcy
Requires-Dist: gitpython
Requires-Dist: jupyterlab (~=2.0)
Requires-Dist: notebook
Requires-Dist: pygithub
Requires-Dist: requests
Requires-Dist: stacklog
Requires-Dist: tenacity
Requires-Dist: tornado
Requires-Dist: importlib-metadata ; python_version < "3.8"
Provides-Extra: dev
Requires-Dist: bump2version (>=1.0.0) ; extra == 'dev'
Requires-Dist: pip (>=9.0.1) ; extra == 'dev'
Requires-Dist: flake8 (>=3.5.0) ; extra == 'dev'
Requires-Dist: isort (<=4.3.9,>=4.3.4) ; extra == 'dev'
Requires-Dist: twine (>=1.10.0) ; extra == 'dev'
Requires-Dist: wheel (>=0.30.0) ; extra == 'dev'
Requires-Dist: coverage (>=4.5.1) ; extra == 'dev'
Requires-Dist: pytest (>=3.4.2) ; extra == 'dev'
Requires-Dist: pytest-cov (>=2.6) ; extra == 'dev'
Provides-Extra: test
Requires-Dist: coverage (>=4.5.1) ; extra == 'test'
Requires-Dist: pytest (>=3.4.2) ; extra == 'test'
Requires-Dist: pytest-cov (>=2.6) ; extra == 'test'
